<?xml version="1.0" encoding="UTF-8"?>
<text id="05-examples" title="Blurred Roles and Team Evolution Examples" version="1.1.0" est_tokens="900" depth="reference">
  <summary>End-to-end worked example: from trigger through validated artefact.</summary>
  <example trace="happy-path">
    <step>Trigger: preconditions in Applies-If hold; Skip-If clean.</step>
    <step>Gather typed inputs per Prerequisites; cite each.</step>
    <step>Draft artefact per content/02-output-contract.xml schema.</step>
    <step>Run validator; address VIOLATION lines.</step>
    <step>Register artefact; notify named reviewer for sign-off.</step>
    <artefact lang="json">
      <code><![CDATA[{
  "report_id": "blurred-acme-2026q2",
  "owner": "hr@acme.io",
  "last_touched": "2026-05-23T11:00:00Z",
  "roles": [
    {
      "id": "pm",
      "title": "Product Manager",
      "headcount": 1
    },
    {
      "id": "eng-lead",
      "title": "Eng Lead",
      "headcount": 1
    },
    {
      "id": "design-lead",
      "title": "Design Lead",
      "headcount": 1
    },
    {
      "id": "data",
      "title": "Data Analyst",
      "headcount": 1
    }
  ],
  "overlap_map": [
    {
      "from": "pm",
      "to": "eng-lead",
      "areas": [
        "prompt-engineering",
        "spec authoring"
      ],
      "evidence": "interview 1:1 2026-05"
    }
  ],
  "ownership_gaps": [
    {
      "area": "ML evaluation harness",
      "evidence": "decision log 2026-04 nobody approved"
    }
  ],
  "duplications": [
    {
      "area": "competitor analysis",
      "owners": [
        "pm",
        "design-lead"
      ],
      "evidence": "two parallel reports 2026-04"
    }
  ],
  "recommendations": [
    {
      "action": "Hire ML PM",
      "owner": "cpo@acme.io",
      "due_cycle": "2026-Q3"
    }
  ],
  "template_version": "1.1.0",
  "status": "ready_for_review"
}]]></code>
    </artefact>
  </example>
  <example trace="skip-path">
    <step>Trigger: one or more Skip-If conditions fire.</step>
    <step>Decision tree routes to conclusion ref='skip-this-methodology'.</step>
    <step>Document skip rationale with the matching rule reference; no artefact emitted.</step>
  </example>
</text>
