<?xml version="1.0" encoding="UTF-8"?>
<text id="06-decision-tree" title="Workflow Design Phase Decision Tree" version="1.1.0" est_tokens="500" depth="essential">
  <summary>Routing tree mapping observable input signals to a conclusion that references a rule from 01-core-rules.xml.</summary>

  <decision-tree>

    <root-question id="q-applies">Do ALL Applies-If conditions hold AND NO Skip-If condition triggers?</root-question>

    <branch when="applies_if == true AND skip_if == false">
      <question id="q-spec-accepted">Is spec.md frontmatter status == "Accepted"?</question>
      <branch when="spec_status == accepted">
        <question id="q-components">Does the feature touch ≥3 components OR require ≥2 architectural trade-offs?</question>
        <branch when="needs_design_doc == true">
          <conclusion ref="r1-spec-accepted" verdict="apply the methodology; produce design.md and validate it."/>
        </branch>
        <branch when="needs_design_doc == false">
          <conclusion ref="skip-this-methodology" verdict="skip the full design phase; author a single TASK directly."/>
        </branch>
      </branch>
      <branch when="spec_status != accepted">
        <conclusion ref="r1-spec-accepted" verdict="defer; wait until spec is Accepted before starting design."/>
      </branch>
    </branch>

    <branch when="applies_if == false OR skip_if == true">
      <conclusion ref="skip-this-methodology" verdict="do not apply this methodology in this context; route to the correct one or skip."/>
    </branch>

  </decision-tree>

  <example trace="happy-path">
    Applies-If holds, Skip-If clear → spec.md is Accepted → feature touches 3+ components with real trade-offs → run the design phase, emit design.md, validate.
  </example>
</text>
