<?xml version="1.0" encoding="UTF-8"?>
<text id="06-decision-tree" title="Trunk-Based CI Gates Decision Tree" version="2.0.0" est_tokens="600" depth="essential">
  <summary>Routing tree mapping observable signals to a rule from 01-core-rules.xml for trunk-based-ci-gates.</summary>
  <decision-tree>
    <root-question id="q-root">Which gate?</root-question>
    <branch when="gate == pre_commit">
      <conclusion ref="pre-commit-under-1s" verdict="fast hooks only (lint + format + secret-scan); no test runner" />
    </branch>
    <branch when="gate == ci_workflow">
      <conclusion ref="ci-under-10-min" verdict="parallelise + cache + nightly slow tier; target p95 &lt; 10 min" />
    </branch>
    <branch when="gate == branch_protection">
      <conclusion ref="branch-protection-required-status-complete" verdict="required reviews + all jobs + linear history + restrict direct push" />
    </branch>
    <branch when="gate == incident_response">
      <conclusion ref="auto-revert-on-red-trunk" verdict="bot revert within 15 min; fix-forward in fresh PR" />
    </branch>
    <branch when="gate == secrets">
      <conclusion ref="secret-scan-mandatory" verdict="detect-secrets/gitleaks in pre-commit + CI defence-in-depth" />
    </branch>
  </decision-tree>
  <example trace="bootstrap-new-repo-gates">gate=branch_protection → required reviews=1, required-status=[lint,typecheck,test,build,gitleaks], linear history, no direct push. Rule: branch-protection-required-status-complete.</example>
</text>
