{
  "slug": "weekly-growth-review-rhythm",
  "tier": "solo",
  "domain": "marketing",
  "group": "marketing",
  "version": "1.0.0",
  "status": "active",
  "last_reviewed": "2026-05-23",
  "maintainers": [
    "faion-network"
  ],
  "summary": "Solo growth review ritual: 5-7 metrics, hypothesis log, decision template — operational backbone connecting channel methodologies to compounding outcomes.",
  "content_id": "28f001a090ba46eb",
  "complexity": "medium",
  "produces": "spec",
  "est_tokens": 4400,
  "tags": [
    "weekly-growth-review-rhythm",
    "marketing",
    "solo",
    "rituals"
  ]
}
