{
  "slug": "video-gen-tools",
  "tier": "geek",
  "domain": "ml-engineering",
  "group": "ai-core",
  "version": "1.1.0",
  "status": "active",
  "last_reviewed": "2026-05-22",
  "maintainers": [
    "faion-network"
  ],
  "summary": "Produces VideoGenerationService with Runway / Luma / Replicate adapters, multi-provider fallback, retry, streaming download, and per-provider rate-limit caps.",
  "content_id": "5e7c2a8b9d4f016a",
  "complexity": "deep",
  "produces": "code",
  "est_tokens": 4500,
  "tags": [
    "video-generation",
    "runway",
    "luma",
    "replicate",
    "async",
    "fallback"
  ]
}
