{
  "slug": "focus-groups-ux-research",
  "tier": "pro",
  "domain": "ux",
  "group": "ux",
  "version": "1.1.0",
  "status": "active",
  "last_reviewed": "2026-05-23",
  "maintainers": [
    "faion-network"
  ],
  "summary": "Moderated 6-10 person focus-group report: screener, discussion guide, moderator playbook, session notes, post-process coding into themes with quoted evidence.",
  "content_id": "dc09e1249217592e",
  "complexity": "medium",
  "produces": "report",
  "est_tokens": 4900,
  "tags": [
    "focus-groups",
    "qualitative-research",
    "group-dynamics",
    "concept-testing",
    "language-discovery"
  ]
}
