{
  "slug": "agency-proposal-template-system",
  "tier": "pro",
  "domain": "marketing",
  "group": "marketing",
  "version": "1.1.0",
  "status": "active",
  "last_reviewed": "2026-05-23",
  "maintainers": [
    "faion-network"
  ],
  "summary": "Tiered (Good / Better / Best) anchored-pricing proposal template — sent within 48h of discovery, fixed scope per tier, 6-month minimum, designed to anchor on the middle tier.",
  "content_id": "058163a6c3b3fe6f",
  "complexity": "deep",
  "produces": "spec",
  "est_tokens": 4200,
  "tags": [
    "proposal",
    "agency",
    "sales",
    "tiered-pricing",
    "sow",
    "anchored-pricing"
  ]
}
