{
  "slug": "aws-iam-security-foundations",
  "tier": "pro",
  "domain": "infra",
  "group": "infra",
  "version": "1.1.0",
  "status": "active",
  "last_reviewed": "2026-05-23",
  "maintainers": [
    "faion-network"
  ],
  "summary": "Baseline IAM hygiene: root account hardened, CloudTrail org-wide multi-region, GuardDuty + Security Hub enabled, password policy + MFA + access-key rotation policy, AWS Config rules pinned to CIS baseline.",
  "content_id": "c4f0aec8262d321b",
  "complexity": "deep",
  "produces": "spec",
  "est_tokens": 5000,
  "tags": [
    "aws",
    "iam",
    "security",
    "root",
    "cloudtrail",
    "infra"
  ]
}
