{
  "slug": "continuous-discovery-habits-product-planning",
  "tier": "pro",
  "domain": "pm",
  "group": "product",
  "version": "1.1.0",
  "status": "active",
  "last_reviewed": "2026-05-23",
  "maintainers": [
    "faion-network"
  ],
  "summary": "Teresa Torres' framework: a product trio (PM + Design Lead + Tech Lead) runs weekly customer touchpoints and maps all signals into an Opportunity Solution Tree (OST).",
  "content_id": "ff40be6332b952b3",
  "complexity": "deep",
  "produces": "spec",
  "est_tokens": 4000,
  "tags": [
    "discovery",
    "product-trio",
    "opportunity-solution-tree",
    "torres",
    "customer-research"
  ]
}
