{
  "slug": "iac-patterns-dry",
  "tier": "pro",
  "domain": "infra",
  "group": "infra",
  "version": "1.1.0",
  "status": "active",
  "last_reviewed": "2026-05-23",
  "maintainers": [
    "faion-network"
  ],
  "summary": "DRY rubric (config) for IaC repos: when to factor (rule of three), for_each over copy-paste, locals + module inputs, env-overlay via tfvars/Pulumi stack config.",
  "content_id": "59b4afe953f1d219",
  "complexity": "medium",
  "produces": "rubric",
  "est_tokens": 3200,
  "tags": [
    "iac",
    "terraform",
    "dry",
    "for-each",
    "locals"
  ]
}
