<?xml version="1.0" encoding="UTF-8"?>
<text id="06-decision-tree" title="Jenkins Pipeline Patterns Decision Tree" version="1.1.1" est_tokens="600" depth="essential">
  <summary>Routing tree mapping observable signals (pipeline count, library presence, parallelism need) to a rule from 01-core-rules.xml.</summary>
  <decision-tree>
    <root-question id="q-applies">Top-level syntax in the existing Jenkinsfile?</root-question>
    <branch when="style == top_level_scripted">
      <conclusion ref="declarative-with-script-escape" verdict="rewrite top-level as Declarative; move scripted into script{} with a justification comment"/>
    </branch>
    <branch when="style == declarative AND duplicated == true AND library_in_app_repo == true">
      <conclusion ref="shared-lib-dedicated-repo" verdict="extract library to dedicated repo; vars/+src/+resources/+test/ layout; tag v1.0.0"/>
    </branch>
    <branch when="style == declarative AND duplicated == true AND library_in_app_repo == false AND pinned == false">
      <conclusion ref="library-version-pinned" verdict="replace @main with semver tag; disable implicit loading"/>
    </branch>
    <branch when="style == declarative AND duplicated == true AND library_in_app_repo == false AND pinned == true AND parallel == true">
      <conclusion ref="parallel-workspace-isolation" verdict="wrap each branch in dir() or ws(); lock() shared external resources"/>
    </branch>
    <branch when="style == declarative AND duplicated == true AND library_in_app_repo == false AND pinned == true AND parallel == false">
      <conclusion ref="options-required" verdict="confirm options{} block has timeout + buildDiscarder + disableConcurrentBuilds + timestamps"/>
    </branch>
    <branch when="style == declarative AND duplicated == false AND agent == kubernetes">
      <conclusion ref="pod-resources-required" verdict="enforce requests + limits on every container; privileged only on explicit dind"/>
    </branch>
    <branch when="style == declarative AND duplicated == false AND agent != kubernetes">
      <conclusion ref="options-required" verdict="confirm options{} block is complete"/>
    </branch>
    <branch when="applies_if == false OR skip_if == true">
      <conclusion ref="skip-this-methodology" verdict="preconditions not met; route to correct methodology or skip."/>
    </branch>
  </decision-tree>
  <example trace="brownfield-scripted-monolith">style=top_level_scripted → rewrite as Declarative → extract dup logic to dedicated library → pin v1.0.0 → wrap parallel branches in dir() → enforces all 6 rules.</example>
</text>
