{
  "__faion_header__": {
    "purpose": "Scoring matrix JSON skeleton",
    "consumes": "See content/02-output-contract.xml inputs",
    "produces": "artefact conforming to content/02-output-contract.xml for produces=decision-record",
    "depends-on": "content/01-core-rules.xml",
    "token-budget-impact": "~200-1000 tokens when loaded as context"
  },
  "artefact_id": "ai-feature-build-buy-finetune-decision-template-001",
  "produced_at": "2026-05-23T10:00:00Z",
  "validator_passed": false,
  "fields": "fill per content/02-output-contract.xml schema"
}
