{
  "slug": "nosql-redis-patterns",
  "tier": "pro",
  "domain": "backend",
  "group": "dev",
  "version": "1.1.0",
  "status": "active",
  "last_reviewed": "2026-05-23",
  "maintainers": [
    "faion-network"
  ],
  "summary": "Pick the right Redis structure per access pattern: strings for caching, hashes for object fields, lists/streams for queues, sorted sets for sliding-window rate limits, with TTLs on every key.",
  "content_id": "700b75279bdae225",
  "complexity": "medium",
  "produces": "spec",
  "est_tokens": 4400,
  "tags": [
    "redis",
    "nosql",
    "caching",
    "rate-limiting",
    "pub-sub"
  ]
}
