{
  "slug": "lb-algorithms",
  "tier": "pro",
  "domain": "infra",
  "group": "infra",
  "version": "1.1.0",
  "status": "active",
  "last_reviewed": "2026-05-23",
  "maintainers": [
    "faion-network"
  ],
  "summary": "Generates a load-balancing algorithm choice (round-robin, weighted RR, least-conn, weighted LC, least-response-time) + LB config snippet driven by traffic profile.",
  "content_id": "23d7fefc662aa393",
  "complexity": "medium",
  "produces": "config",
  "est_tokens": 4800,
  "tags": [
    "load-balancing",
    "algorithms",
    "round-robin",
    "least-connections",
    "infrastructure"
  ]
}
