<?xml version="1.0" encoding="UTF-8"?>
<text id="06-decision-tree" title="Async Standup Methodology Decision Tree" version="1.0.0" est_tokens="500" depth="essential">
  <summary>Routing tree mapping observable inputs to a rule from `01-core-rules.xml`. MANDATORY for every methodology — even flat ones — per F-066 DoD.</summary>

  <decision-tree>
    <root-question id="q-root">Team distributed across ≥2 timezones AND ≥2 daily contributors?</root-question>
    <branch when="timezone_count &gt;= 2 AND daily_contributors &gt;= 2">
      <question id="q-sub">Does a shared channel exist with admin write-access?</question>
      <branch when="shared_channel_exists == true AND admin_access == true">
        <conclusion ref="r1-three-questions"/>
      </branch>
      <branch when="NOT (shared_channel_exists == true AND admin_access == true)">
        <conclusion ref="skip-this-methodology"/>
      </branch>
    </branch>
    <branch when="timezone_count &lt; 2 OR daily_contributors &lt; 2">
      <conclusion ref="skip-this-methodology"/>
    </branch>
  </decision-tree>

  <example trace="apply-path">
    All preconditions satisfied → conclusion r1-three-questions.
  </example>
</text>
