<?xml version="1.0" encoding="UTF-8"?>
<playbook id="01-playbook" slug="friday-bug-bash-triage" goal="operate-ritual" complexity="light">
  <intent>Open bug tracker + sprawling debt list → grouped, severity-tagged, top-3 resolved or queued.</intent>
  <scope>60-minute Friday ritual: Sentry / GitHub issues grouped, severity-tagged, top-3 fixed or queued, debt list updated with one decision per item (fix now / accept / kill). Exit artifact is clean tracker view + updated debt log.</scope>
  <success-criteria>
    <criterion>All open issues have severity tag</criterion>
    <criterion>Top 3 issues either fixed or scheduled with owner</criterion>
    <criterion>Debt log: every item has decision (fix-now / accept / kill)</criterion>
    <criterion>Ritual completed in ≤60 minutes</criterion>
  </success-criteria>
  <stages>
    <stage n="1" name="Group">
      <intent>Cluster bugs by theme; surface duplicates.</intent>
      <tasks>
        <task>Pull open issues + Sentry events</task>
        <task>Tag by theme + severity</task>
        <task>Merge duplicates</task>
      </tasks>
      <methodologies>
        <ref slug="logging-patterns" />
        <ref slug="feedback-management" />
        <ref slug="backlog-management" />
      </methodologies>
      <outputs>
        <output>Grouped issue list</output>
      </outputs>
      <decision-gate>Advance when every issue has theme + severity. Refuse to skip — solo founders accumulate noise fast.</decision-gate>
    </stage>
    <stage n="2" name="Decide">
      <intent>One decision per item: fix now, accept, or kill.</intent>
      <tasks>
        <task>Score top items against impact + effort</task>
        <task>Write decision per item</task>
        <task>Update debt log</task>
      </tasks>
      <methodologies>
        <ref slug="tech-debt-basics" />
        <ref slug="tech-debt-management" />
        <ref slug="technical-debt" />
        <ref slug="technical-debt-management" />
        <ref slug="refactoring-patterns" />
        <ref slug="architecture-decision-records" />
      </methodologies>
      <outputs>
        <output>Debt log with decisions</output>
      </outputs>
      <decision-gate>Advance when every top-10 item has a decision. No 'maybe later'.</decision-gate>
    </stage>
    <stage n="3" name="Ship">
      <intent>Fix the top-3 chosen items inside the hour.</intent>
      <tasks>
        <task>Pick 3 with highest impact-per-effort</task>
        <task>Ship with feature flag if risky</task>
        <task>Push to staging</task>
      </tasks>
      <methodologies>
        <ref slug="feature-flags" />
      </methodologies>
      <outputs>
        <output>3 fixes shipped</output>
      </outputs>
      <decision-gate>Required output: 3 PRs merged. Defer remainder to next week's bash.</decision-gate>
    </stage>
  </stages>
  <gaps>
    <gap slug="solo-bug-triage-rubric" expected-tier="solo" />
    <gap slug="sentry-alert-routing-for-solos" expected-tier="solo" />
  </gaps>
  <extra key="context" value="[solo]" />
  <extra key="non_goals" value="['Major refactors — debt items get queued, not executed', Customer-facing comms — separate inbox-sweep playbook]" />
  <extra key="prerequisites" value="['Issue tracker exists (GitHub, Linear, or similar)', Sentry/logging in place (monitoring-logging complete)]" />
  <extra key="common_pitfalls" value="[Trying to fix all of them — guarantees nothing ships, Leaving items without decision — they rot in the backlog]" />
  <extra key="quality_checklist" value="['Did every item I touched get a decision, or did I leave some ''open''?', 'Are the 3 I fixed actually high-impact, or just easy?']" />
  <extra key="related_playbooks" value="[sunday-roadmap-ritual, deploy-day-staging-to-prod]" />
  <extra key="token_budget_estimate" value="8000" />
  <extra key="cli_invocations" value="{human: faion get-content friday-bug-bash-triage --format md, agent: faion get-content friday-bug-bash-triage --format context, json: faion get-content friday-bug-bash-triage --format json}" />
  <extra key="changelog" value="[{version: 0.1.0, date: 2026-05-20, note: Initial draft for F-064 P1 solo SaaS builder persona}]" />
</playbook>
