{
  "slug": "elicitation-techniques",
  "tier": "pro",
  "domain": "ba",
  "group": "ba",
  "version": "1.1.0",
  "status": "active",
  "last_reviewed": "2026-05-23",
  "maintainers": [
    "faion-network"
  ],
  "summary": "Triangulated elicitation pipeline (interview/workshop/observation/survey/prototype/focus-group/brainstorm) producing typed session artifacts and REQ stubs that cite ≥2 distinct techniques per requirement.",
  "content_id": "12b5c60e5614f7c4",
  "complexity": "deep",
  "produces": "report",
  "est_tokens": 5000,
  "tags": [
    "elicitation",
    "requirements",
    "stakeholder-engagement",
    "discovery",
    "triangulation"
  ]
}
