{
  "slug": "change-request-impact-assessment",
  "tier": "pro",
  "domain": "govern-decide",
  "group": "business-analyst",
  "version": "1.0.0",
  "status": "draft",
  "last_reviewed": "2026-05-22",
  "maintainers": [
    "faion-network"
  ],
  "summary": "One incoming CR ends with a written impact analysis covering scope, traceability deltas, risks, effort signal, and a clear go/no-go recommendation.",
  "content_id": "75fc42a0849cda57",
  "complexity": "medium",
  "produces": "plan",
  "est_tokens": 2000,
  "tags": []
}
