<?xml version="1.0" encoding="UTF-8"?>
<text id="05-examples" title="Instagram Ads Playbook Worked Example" version="1.1.0" est_tokens="800" depth="medium">
  <summary>One end-to-end worked example showing the methodology applied to a realistic scenario, including the produced artefact.</summary>
  <example type="good">
    <description>Faion DTC beauty launch. Reels 60% / Stories 20 / Feed 20. UGC for cold. 9:16 primary. Shopping tags on.</description>
    <code lang="json"><![CDATA[
{
  "placements": {
    "reels_pct": 60,
    "stories_pct": 20,
    "feed_pct": 20
  },
  "creative_strategy": {
    "primary_format": "9:16",
    "cold_content_type": "ugc"
  },
  "frequency_caps": {
    "cold_per_week": 3,
    "retarget_per_week": 5
  },
  "shopping_tags": {
    "enabled": true
  }
}
    ]]></code>
    <note>Reels-first respected; UGC cold; frequency caps in band; Shopping tags enabled.</note>
  </example>
</text>
