<?xml version="1.0" encoding="UTF-8"?>
<text id="06-decision-tree" title="Instagram Ads Playbook Decision Tree" version="1.1.0" est_tokens="600" depth="essential">
  <summary>Routing tree on observable signals. Every leaf <conclusion ref="..."/> points to a rule id from 01-core-rules.xml.</summary>
  <decision-tree>
    <root-question id="q-root">Is audience B2C / lifestyle / DTC with IG as primary surface?</root-question>
    <branch when="audience mismatch">
      <conclusion ref="reels-first" verdict="skip-this-methodology; defer until preconditions met"/>
    </branch>
    <branch when="audience_fit">
      <question id="q-content">Is UGC / creator pipeline available?</question>
      <branch when="answer == yes">
        <conclusion ref="ugc-or-creator-cold" verdict="ship UGC/creator on Reels 60%+ for cold; brand-polished for retarget"/>
      </branch>
      <branch when="answer == no">
        <conclusion ref="ugc-or-creator-cold" verdict="restrict to retargeting only until UGC pipeline ready"/>
      </branch>
    </branch>
  </decision-tree>
  <example trace="dtc-launch">
    B2C beauty DTC, UGC pipeline ready → Reels-first 60%, UGC for cold.
  </example>
</text>
