{
  "slug": "privacy-compliance",
  "tier": "pro",
  "domain": "marketing",
  "group": "marketing",
  "version": "1.1.0",
  "status": "active",
  "last_reviewed": "2026-05-23",
  "maintainers": [
    "faion-network"
  ],
  "summary": "Privacy-by-default analytics setup: CMP with deny-default consent, GA4 Consent Mode v2 wiring, CCPA GPC signal handling, IP anonymization, and a tag-firing audit log.",
  "content_id": "b44f392c25727ca4",
  "complexity": "deep",
  "produces": "config",
  "est_tokens": 4200,
  "tags": [
    "privacy",
    "gdpr",
    "ccpa",
    "analytics",
    "consent",
    "tracking"
  ]
}
