{
  "__faion_header__": {
    "purpose": "JSON Schema for the Solo Content Calendar Template output contract",
    "consumes": "subagent-produced artefact JSON",
    "produces": "validation verdict (pass/fail with violations)",
    "depends-on": "content/02-output-contract.xml",
    "token-budget-impact": "~250 tokens"
  },
  "$schema": "http://json-schema.org/draft-07/schema#",
  "$id": "https://faion.network/schema/solo-content-calendar-template.json",
  "title": "Solo Content Calendar Template Output Contract",
  "type": "object",
  "required": [
    "operator",
    "rows",
    "primary_channel",
    "quarterly_review_date",
    "friday_gate_enabled",
    "version",
    "last_reviewed"
  ],
  "properties": {
    "operator": {
      "type": "string",
      "description": "named accountable owner"
    },
    "rows": {
      "type": "array",
      "description": "exactly 12 rows with week_iso + pain_ref + asset_type + channel + status",
      "items": {
        "type": "object"
      },
      "minItems": 1
    },
    "primary_channel": {
      "type": "string",
      "description": "seo|newsletter|x|linkedin|build-in-public"
    },
    "quarterly_review_date": {
      "type": "string",
      "description": "ISO date for retirement audit",
      "format": "date"
    },
    "friday_gate_enabled": {
      "type": "boolean",
      "description": "must be true"
    },
    "version": {
      "type": "string",
      "description": "semver"
    },
    "last_reviewed": {
      "type": "string",
      "description": "ISO date",
      "format": "date"
    }
  },
  "additionalProperties": true
}
