{
  "slug": "ops-upselling-cross-selling",
  "tier": "pro",
  "domain": "marketing",
  "group": "marketing",
  "version": "1.1.0",
  "status": "active",
  "last_reviewed": "2026-05-23",
  "maintainers": [
    "faion-network"
  ],
  "summary": "Expansion-revenue playbook-step: detect usage triggers (80% of limit, advanced feature, team growth), match trigger to upgrade offer framed on the customer's own data point, one-click upgrade with proration, monthly NRR tracking.",
  "content_id": "f095278ba1d235e1",
  "complexity": "medium",
  "produces": "playbook-step",
  "est_tokens": 4200,
  "tags": [
    "upselling",
    "cross-selling",
    "expansion-revenue",
    "customer-success",
    "pricing-strategy"
  ]
}
