{
  "__faion_header__": {
    "purpose": "Skeleton artefact for the SDD Workflow Overview methodology output",
    "consumes": "Inputs declared in AGENTS.md → Prerequisites",
    "produces": "spec",
    "depends-on": "content/01-core-rules.xml, content/02-output-contract.xml",
    "token-budget-impact": "low — single JSON file, ≤300 tokens"
  },
  "artefact_id": "sdd-workflow-overview-example",
  "version": "1.0.0",
  "last_reviewed": "2026-05-23",
  "owner": "@solo-founder",
  "feature_id": "F-example",
  "summary": "One-paragraph problem + outcome statement.",
  "items": [
    "item-1",
    "item-2",
    "item-3"
  ],
  "out_of_scope": [
    "item-x",
    "item-y"
  ]
}