{
  "slug": "template-design",
  "tier": "solo",
  "domain": "sdd",
  "group": "sdd",
  "version": "1.0.0",
  "status": "active",
  "last_reviewed": "2026-05-23",
  "maintainers": [
    "faion-network"
  ],
  "summary": "Maintain the canonical design.md template as a versioned, lintable Markdown skeleton so every team-authored design doc starts from the same shape.",
  "content_id": "601f7095198597ac",
  "complexity": "light",
  "produces": "config",
  "est_tokens": 2900,
  "tags": [
    "template",
    "design-doc",
    "skeleton",
    "version-controlled",
    "lint"
  ]
}
