{
  "slug": "secrets-management",
  "tier": "pro",
  "domain": "infra",
  "group": "infra",
  "version": "1.1.0",
  "status": "active",
  "last_reviewed": "2026-05-23",
  "maintainers": [
    "faion-network"
  ],
  "summary": "Secrets management spec: eliminate static credentials, use cloud identity (IRSA / Workload Identity / OIDC), short-lived dynamic credentials, 30-day rotation, ESO for Kubernetes injection.",
  "content_id": "5646b8f8e846e9ab",
  "complexity": "medium",
  "produces": "config",
  "est_tokens": 3900,
  "tags": [
    "secrets",
    "vault",
    "kubernetes",
    "oidc",
    "eso"
  ]
}
