{
  "slug": "project-closure-with-lessons-extraction",
  "tier": "pro",
  "domain": "pm",
  "group": "pm",
  "version": "1.1.0",
  "status": "active",
  "last_reviewed": "2026-05-23",
  "maintainers": [
    "faion-network"
  ],
  "summary": "Pinned closure method for distressed-project rescues — outcome-vs-charter variance, behavioural-change lessons with named owners, follow-up items, and reviewable artefact at the next iteration.",
  "content_id": "c991f7f6ac8ef1cb",
  "complexity": "deep",
  "produces": "report",
  "est_tokens": 4400,
  "tags": [
    "closure",
    "lessons-learned",
    "postmortem",
    "distressed-project"
  ]
}
