{
  "slug": "acceptance-criteria-ba-modeling",
  "tier": "pro",
  "domain": "ba",
  "group": "ba",
  "version": "1.1.0",
  "status": "active",
  "last_reviewed": "2026-05-23",
  "maintainers": [
    "faion-network"
  ],
  "summary": "Produces stable, testable acceptance criteria (Given/When/Then or rule-based) with cross-reference IDs (AC-FEATURE-NN) tying spec, test-plan, and CI report.",
  "content_id": "bf2825eff769aa87",
  "complexity": "medium",
  "produces": "spec",
  "est_tokens": 4300,
  "tags": [
    "acceptance-criteria",
    "spec",
    "testing",
    "bdd",
    "gherkin"
  ]
}
