<?xml version="1.0" encoding="UTF-8"?>
<text id="06-decision-tree" title="Schedule Development Decision Tree" version="1.1.1" est_tokens="500" depth="essential">
  <summary>Decision tree mapping schedule state to a rule.</summary>
  <decision-tree>
    <root-question id="q-applies">Is every activity name verb-led?</root-question>
    <branch when="verb_led_all == false">
      <conclusion ref="verb-led-activities" verdict="rename non-verb activities before continuing"/>
    </branch>
    <branch when="verb_led_all == true AND pert_compliance == false">
      <conclusion ref="pert-over-5-days" verdict="apply three-point estimates on long activities"/>
    </branch>
    <branch when="verb_led_all == true AND pert_compliance == true AND links_typed == false">
      <conclusion ref="dep-types-explicit" verdict="reject untyped links"/>
    </branch>
    <branch when="verb_led_all == true AND pert_compliance == true AND links_typed == true AND buffers_visible == false">
      <conclusion ref="buffers-visible" verdict="extract hidden padding into named buffers"/>
    </branch>
    <branch when="verb_led_all == true AND pert_compliance == true AND links_typed == true AND buffers_visible == true AND days_since_refresh &gt; 14">
      <conclusion ref="weekly-refresh" verdict="flag stale; refresh schedule"/>
    </branch>
    <branch when="verb_led_all == true AND pert_compliance == true AND links_typed == true AND buffers_visible == true AND days_since_refresh &lt;= 14">
      <conclusion ref="verb-led-activities" verdict="accept schedule"/>
    </branch>
    <branch when="applies_if == false OR skip_if == true">
      <conclusion ref="skip-this-methodology" verdict="preconditions not met; route to correct methodology or skip."/>
    </branch>
  </decision-tree>
  <example trace="data-platform">verb_led_all=true, pert_compliance=true, links_typed=true, buffers_visible=true, days_since_refresh=3 → accept schedule.</example>
</text>
