{
  "slug": "sunset-failed-product-playbook",
  "tier": "solo",
  "domain": "product",
  "group": "product",
  "version": "1.0.0",
  "status": "active",
  "last_reviewed": "2026-05-23",
  "maintainers": [
    "faion-network"
  ],
  "summary": "End-to-end sunset playbook: refund policy, customer migration plan, domain reuse / archive, asset salvage, public retro — shutters a failing product gracefully and reclaims learning + leverage for the next bet.",
  "content_id": "f8fabace1f007c94",
  "complexity": "medium",
  "produces": "playbook-step",
  "est_tokens": 3600,
  "tags": [
    "sunset-failed-product-playbook",
    "shutdown",
    "retro",
    "solo"
  ]
}
