{
  "slug": "a11y-screen-status-tracker",
  "tier": "pro",
  "domain": "ux",
  "group": "ux",
  "version": "1.1.0",
  "status": "active",
  "last_reviewed": "2026-05-23",
  "maintainers": [
    "faion-network"
  ],
  "summary": "Per-screen accessibility status tracker (pass / partial / fail) with owner + last-tested + remediation plan for every named screen.",
  "content_id": "ba30495e22b713ff",
  "complexity": "medium",
  "produces": "report",
  "est_tokens": 4100,
  "tags": [
    "a11y",
    "tracker",
    "screen-status",
    "audit",
    "ux"
  ]
}
